Metadata-Version: 2.4
Name: collm-hep
Version: 0.1.0
Summary: An Automated, End-to-End Deep Learning Toolbox for Collider Physics Analysis
Author: CoLLM Authors
Maintainer: CoLLM Authors
License-Expression: MIT
Project-URL: Homepage, https://github.com/yourusername/CoLLM
Project-URL: Documentation, https://github.com/yourusername/CoLLM#readme
Project-URL: Repository, https://github.com/yourusername/CoLLM
Project-URL: Issues, https://github.com/yourusername/CoLLM/issues
Keywords: particle-physics,LHCO,LLM,code-generation,deep-learning,HEP,collider-physics,machine-learning,automation
Classifier: Development Status :: 4 - Beta
Classifier: Intended Audience :: Science/Research
Classifier: Operating System :: OS Independent
Classifier: Programming Language :: Python :: 3
Classifier: Programming Language :: Python :: 3.11
Classifier: Programming Language :: Python :: 3.12
Classifier: Topic :: Scientific/Engineering :: Physics
Classifier: Topic :: Scientific/Engineering :: Artificial Intelligence
Requires-Python: >=3.11
License-File: LICENSE
Requires-Dist: numpy<2
Requires-Dist: matplotlib
Requires-Dist: tqdm
Requires-Dist: pyyaml
Requires-Dist: transformers>=4.36.0
Requires-Dist: huggingface-hub>=0.20.0
Requires-Dist: accelerate>=0.25.0
Requires-Dist: pydantic>=2.0.0
Requires-Dist: torch>=2.0.0
Requires-Dist: streamlit>=1.28.0
Provides-Extra: langchain
Requires-Dist: langchain>=0.1.0; extra == "langchain"
Requires-Dist: langchain-huggingface>=0.0.1; extra == "langchain"
Provides-Extra: dev
Requires-Dist: pytest>=7.0.0; extra == "dev"
Requires-Dist: pytest-cov>=4.0.0; extra == "dev"
Requires-Dist: black>=23.0.0; extra == "dev"
Requires-Dist: ruff>=0.1.0; extra == "dev"
Requires-Dist: mypy>=1.0.0; extra == "dev"
Provides-Extra: all
Requires-Dist: collm-hep[dev,langchain]; extra == "all"
Dynamic: license-file
